odoo/addons/sale_report_salesperson_from_partner/README.rst
odoo/addons/sale_report_salesperson_from_partner/__init__.py
odoo/addons/sale_report_salesperson_from_partner/__manifest__.py
odoo/addons/sale_report_salesperson_from_partner/i18n/es.po
odoo/addons/sale_report_salesperson_from_partner/i18n/it.po
odoo/addons/sale_report_salesperson_from_partner/i18n/sale_report_salesperson_from_partner.pot
odoo/addons/sale_report_salesperson_from_partner/readme/CONTRIBUTORS.md
odoo/addons/sale_report_salesperson_from_partner/readme/DESCRIPTION.md
odoo/addons/sale_report_salesperson_from_partner/report/__init__.py
odoo/addons/sale_report_salesperson_from_partner/report/sale_report.py
odoo/addons/sale_report_salesperson_from_partner/static/description/icon.png
odoo/addons/sale_report_salesperson_from_partner/static/description/index.html
odoo/addons/sale_report_salesperson_from_partner/tests/__init__.py
odoo/addons/sale_report_salesperson_from_partner/tests/test_sale_report_salesperson_from_partner.py
odoo/addons/sale_report_salesperson_from_partner/views/sale_report_views.xml
odoo_addon_sale_report_salesperson_from_partner-18.0.1.0.0.2.dist-info/METADATA
odoo_addon_sale_report_salesperson_from_partner-18.0.1.0.0.2.dist-info/WHEEL
odoo_addon_sale_report_salesperson_from_partner-18.0.1.0.0.2.dist-info/top_level.txt
odoo_addon_sale_report_salesperson_from_partner-18.0.1.0.0.2.dist-info/RECORD
